README.md
setup.py
corpona/__init__.py
corpona/explorer.py
corpona/summary.py
corpona/xml.py
corpona.egg-info/PKG-INFO
corpona.egg-info/SOURCES.txt
corpona.egg-info/dependency_links.txt
corpona.egg-info/not-zip-safe
corpona.egg-info/requires.txt
corpona.egg-info/top_level.txt