Metadata-Version: 2.1
Name: corpona
Version: 1.0.1
Summary: A library for reading corpora.
Home-page: https://github.com/mokha/corpona
Author: Khalid Alnajjar
Author-email: khldalnajjar@gmail.com
License: Apache License, Version 2.0
Project-URL: Bug Reports, https://github.com/mokha/corpona/issues
Project-URL: Wiki, https://github.com/mokha/corpona/wiki
Project-URL: Developer, https://www.khalidalnajjar.com/
Keywords: NLP,corpus,processing,corpora,reading
Platform: UNKNOWN
Classifier: Development Status :: 5 - Production/Stable
Classifier: Intended Audience :: Developers
Classifier: Intended Audience :: Science/Research
Classifier: Topic :: Text Processing :: Linguistic
Classifier: Programming Language :: Python :: 3
